MANIFEST.in
README.md
requirements-dev.txt
requirements.txt
setup.cfg
setup.py
django_pedant.egg-info/PKG-INFO
django_pedant.egg-info/SOURCES.txt
django_pedant.egg-info/dependency_links.txt
django_pedant.egg-info/not-zip-safe
django_pedant.egg-info/requires.txt
django_pedant.egg-info/top_level.txt
pedant/__init__.py
pedant/decorators.py
pedant/tests.py
pedant/utils.py
pedant/templatetags/__init__.py
pedant/templatetags/pedant_tags.py