Metadata-Version: 1.0
Name: django-pedant
Version: 1.0.1
Summary: Make django templates fail fast on errors
Home-page: https://github.com/counsyl/django-pedant
Author: Counsyl
Author-email: root@counsyl.com
License: UNKNOWN
Platform: UNKNOWN
